[{"source": {"id": "bbc-news", "name": "BBC News"}, "author": "BBC News", "title": "When Amazon packages arrive that you didn't order", "description": "Zoe Kleinman looks at the sneaky way some sellers are trying to boost their products on Amazon.", "url": "http://www.bbc.co.uk/news/technology-55117037", "urlToImage": "https://ichef.bbci.co.uk/images/ic/400xn/p08zww33.jpg", "publishedAt": "2020-12-01T16:07:22.9703667Z", "content": "Have you ever received an Amazon package you did not order?\r\nYou have have been the victim of so-called \"brushing\", whereby unscrupulous online sellers send out goods to people who did not order them\u2026 [+100 chars]"}, {"source": {"id": "bbc-news", "name": "BBC News"}, "author": "BBC News", "title": "Stockholm mother arrested 'after keeping son for decades in flat'", "description": "Swedish police arrest an elderly woman after her adult son is found injured and living in misery.", "url": "http://www.bbc.co.uk/news/world-europe-55146377", "urlToImage": "https://ichef.bbci.co.uk/news/1024/branded_news/C1E3/production/_115753694_policeepa.jpg", "publishedAt": "2020-12-01T15:37:28.5385165Z", "content": "image captionPolice are searching the flat\r\nSwedish police have arrested an elderly woman on suspicion of keeping her son confined to their flat in a Stockholm suburb for nearly three decades.\r\nShe d\u2026 [+2339 chars]"}, {"source": {"id": "bbc-news", "name": "BBC News"}, "author": "BBC News", "title": "China's sample-return Moon mission touches down", "description": "The robotic Chang'e-5 mission makes a soft landing on the lunar nearside.", "url": "http://www.bbc.co.uk/news/science-environment-55148998", "urlToImage": "https://ichef.bbci.co.uk/news/1024/branded_news/2DE1/production/_112154711_breaking.png", "publishedAt": "2020-12-01T15:37:24.305196Z", "content": "By Jonathan AmosBBC Science Correspondent\r\nimage captionArtwork: The mission hopes to pick up a couple of kilos of surface materials\r\nChina says it has successfully put another probe on the Moon. \r\nI\u2026 [+3066 chars]"}]